telekinesis/__init__.py
telekinesis/cornea.py
telekinesis/pupil.py
telekinesis/vitreous.py
telekinesis_ai-0.0.1rc5.dist-info/licenses/LICENSE.txt
utils/__init__.py
utils/profiler.py
telekinesis_ai-0.0.1rc5.dist-info/METADATA
telekinesis_ai-0.0.1rc5.dist-info/WHEEL
telekinesis_ai-0.0.1rc5.dist-info/top_level.txt
telekinesis_ai-0.0.1rc5.dist-info/RECORD
