Metadata-Version: 2.4
Name: telekinesis-ai
Version: 0.0.1rc5
Summary: Official Telekinesis SDK for working with Telekinesis APIs.
Author-email: Telekinesis <support@telekinesis.ai>
License-Expression: Apache-2.0
Project-URL: Homepage, https://telekinesis.ai
Project-URL: Documentation, https://docs.telekinesis.ai
Project-URL: Telekinesis Examples Repository, https://github.com/telekinesis-ai/telekinesis-examples
Classifier: Programming Language :: Python :: 3
Classifier: Programming Language :: Python :: 3.11
Classifier: Programming Language :: Python :: 3.12
Classifier: Operating System :: OS Independent
Classifier: Intended Audience :: Developers
Classifier: Topic :: Software Development :: Libraries
Classifier: Topic :: Scientific/Engineering
Classifier: Topic :: Scientific/Engineering :: Artificial Intelligence
Requires-Python: <3.13,>=3.11
License-File: LICENSE.txt
Requires-Dist: requests>=2.31.0
Requires-Dist: loguru>=0.5.3
Requires-Dist: numpy>=2.0
Requires-Dist: requests-toolbelt
Requires-Dist: psutil
Requires-Dist: telekinesis-datatypes==0.0.1rc4
Provides-Extra: docs
Requires-Dist: mkdocs<2,>=1.6; extra == "docs"
Requires-Dist: mkdocstrings[python]<1,>=0.25; extra == "docs"
Requires-Dist: mkdocs-awesome-pages-plugin<3,>=2; extra == "docs"
Dynamic: license-file
